xlsfile/__init__.py
xlsfile/xlsFile.py
xlsfile_shaw1236-0.0.2.dist-info/LICENSE
xlsfile_shaw1236-0.0.2.dist-info/METADATA
xlsfile_shaw1236-0.0.2.dist-info/WHEEL
xlsfile_shaw1236-0.0.2.dist-info/top_level.txt
xlsfile_shaw1236-0.0.2.dist-info/RECORD
