Metadata-Version: 2.1
Name: xlsfile-shaw1236
Version: 0.0.2
Summary: Utility for read/write of Excel or csv files
Home-page: https://github.com/shaw1236/ExcelFiles
Author: Simon Li
Author-email: shaw1236@gmail.com
License: UNKNOWN
Platform: UNKNOWN
Classifier: Programming Language :: Python :: 3
Classifier: License :: OSI Approved :: MIT License
Classifier: Operating System :: OS Independent
Requires-Python: >=3.6
